<?xml version="1.0" encoding="utf-8"?>
<LanguageData>
  <!--The following translations were generated by https://www.deepl.com/-->
  <!-- EN: asphalt road -->
  <AsphaltRoad.label>Asphaltstraße</AsphaltRoad.label>
  <!-- EN: dirt path+ -->
  <DirtPathBuilt.label>Feldweg</DirtPathBuilt.label>
  <!-- EN: dirt road+ -->
  <DirtRoadBuilt.label>Schotterstraße</DirtRoadBuilt.label>
  <!-- EN: glit overpass -->
  <GlitterOverpass.label>Glit-Überführung</GlitterOverpass.label>
  <!-- EN: glitterrail -->
  <Glitterrail.label>glitterrail</Glitterrail.label>
  <!-- EN: glitter road -->
  <GlitterRoad.label>Glitzerstraße</GlitterRoad.label>
  <!-- EN: glitteryard -->
  <GlitterYard.label>Glitzerhof</GlitterYard.label>
  <!-- EN: railroad -->
  <Railroad.label>Eisenbahn</Railroad.label>
  <!-- EN: rail overpass -->
  <RailroadOverpass.label>Eisenbahnüberführung</RailroadOverpass.label>
  <!-- EN: rail tunnel -->
  <RailTunnel.label>Eisenbahntunnel</RailTunnel.label>
  <!-- EN: railyard -->
  <RailYard.label>Gleisanlage</RailYard.label>
  <!-- EN: stone road+ -->
  <StoneRoadBuilt.label>Steinstraße</StoneRoadBuilt.label>
</LanguageData>
